likeinterface/__init__.py
likeinterface/__meta__.py
likeinterface/exceptions.py
likeinterface/interface.py
likeinterface/network.py
likeinterface/session.py
likeinterface/enums/__init__.py
likeinterface/enums/action.py
likeinterface/enums/position.py
likeinterface/enums/rank.py
likeinterface/enums/round.py
likeinterface/enums/state.py
likeinterface/enums/suit.py
likeinterface/methods/__init__.py
likeinterface/methods/add_collection.py
likeinterface/methods/add_file.py
likeinterface/methods/add_game.py
likeinterface/methods/adjust_game.py
likeinterface/methods/base.py
likeinterface/methods/delete_game.py
likeinterface/methods/execute_action.py
likeinterface/methods/get_balance.py
likeinterface/methods/get_collection.py
likeinterface/methods/get_evaluation_result.py
likeinterface/methods/get_file.py
likeinterface/methods/get_game.py
likeinterface/methods/get_me.py
likeinterface/methods/get_possible_actions.py
likeinterface/methods/get_user.py
likeinterface/methods/join_to_game.py
likeinterface/methods/left_from_game.py
likeinterface/methods/set_balance.py
likeinterface/methods/set_next_game.py
likeinterface/methods/sign_in.py
likeinterface/types/__init__.py
likeinterface/types/action.py
likeinterface/types/authorization.py
likeinterface/types/balance.py
likeinterface/types/base.py
likeinterface/types/cards.py
likeinterface/types/collection.py
likeinterface/types/collection_element.py
likeinterface/types/file.py
likeinterface/types/game.py
likeinterface/types/hand.py
likeinterface/types/input_file.py
likeinterface/types/player.py
likeinterface/types/user.py
likeinterface/utils/__init__.py
likeinterface/utils/response_validator.py
likeinterface-2.5.dist-info/METADATA
likeinterface-2.5.dist-info/WHEEL
likeinterface-2.5.dist-info/RECORD
